pySciTools/__init__.py
pySciTools/cli_gpu_test.py
pySciTools/cli_rename_img_vid.py
pySciTools/nb_utils.py
pySciTools/system_run.py
pySciTools/utils.py
pySciTools/__pycache__/__init__.cpython-310.pyc
pySciTools/__pycache__/nb_utils.cpython-310.pyc
pySciTools/__pycache__/utils.cpython-310.pyc
pyscitools-0.1.9.dist-info/licenses/LICENSE
pyscitools-0.1.9.dist-info/METADATA
pyscitools-0.1.9.dist-info/WHEEL
pyscitools-0.1.9.dist-info/entry_points.txt
pyscitools-0.1.9.dist-info/top_level.txt
pyscitools-0.1.9.dist-info/RECORD
