Metadata-Version: 2.4
Name: pySciTools
Version: 0.1.9
Summary: A simple example library
Author-email: Peng Zhou <zhoupeng23@nuaa.edu.cn>
License-Expression: MIT
Project-URL: Homepage, https://github.com/PeterouZh
Requires-Python: >=3.7
License-File: LICENSE
Requires-Dist: numpy
Requires-Dist: matplotlib
Requires-Dist: tyro
Requires-Dist: easydict
Dynamic: license-file
